{
  "title": "detective conan",
  "url": "https://www.detectiveconanworld.com/wiki/Mini_Air_Tank",
  "infobox": {
    "Japanese name:": "ミニエアータンク",
    "Romaji name:": "Mini Eā Tanku",
    "Created by:": "Professor Agasa",
    "Used by:": "Conan Edogawa  Ran Mouri  Sonoko Suzuki",
    "First appearance:": "Movie 11",
    "Appearances:": "Movies: 1"
  },
  "sections": {
    "Description": "An air tank that can allow Conan to breathe underwater for 10 minutes. This device is possibly based on a similar gadget from the James Bond movieThunderball.\n"
  }
}