{
  "title": "detective conan",
  "url": "https://www.detectiveconanworld.com/wiki/Voice-Changing_Face_Mask",
  "infobox": {
    "Japanese name:": "マスク型変声機",
    "Romaji name:": "Masuku-gata Henseiki",
    "Created by:": "Professor Agasa",
    "Used by:": "Ai HaibaraConan EdogawaYusaku Kudo",
    "First appearance:": "Manga: Volume 26 - File 2  Anime: Episode 190",
    "Appearances:": "Chapters: 4Episodes: 8Openings: 1"
  },
  "sections": {
    "Description": "Haibaraused this voice-changer to aid her disguise as Conan during the Desperate Revival arc. Although not confirmed, it can be saidConanused this gadget to aid his disguise asHaibarain Episode 345.\n"
  }
}